Workbook

Sheet Summary
A1: Credent(By Asenra) · 5-Year Financial Summary
A2: Auto-calculated from P&L · Fill the P&L sheet first
A3: LINE ITEM | B3: FY 2025-26 | C3: FY 2026-27 | D3: FY 2027-28 | E3: FY 2028-29 | F3: FY 2029-30
A4: YOUR STARTUP
A5: Startup Name | B5: Credent (by Asenra)
A6: Founder(s) | B6: Karan Patil & Team
A7: Sector / Industry | B7: FinTech / Banking Technology
A8: Stage | B8: Pre-revenue
A9: City | B9: Mumbai
A10: Funding Raised So Far | B10: ₹ 0 (Bootstrapped)
A12: KEY METRICS (auto-calculated from P&L sheet)
A13: Total Revenue (₹) | B13: ='P&L'!B7 -> 0 | C13: ='P&L'!C7 -> 500000 | D13: ='P&L'!D7 -> 2000000 | E13: ='P&L'!E7 -> 6000000 | F13: ='P&L'!F7 -> 15000000
A14: Gross Profit (₹) | C14: ='P&L'!C13 -> 420000 | D14: ='P&L'!D13 -> 1800000 | E14: ='P&L'!E13 -> 5500000 | F14: ='P&L'!F13 -> 13900000
A15: EBITDA (₹) | C15: ='P&L'!C23 -> -608000 | D15: ='P&L'!D23 -> -250000 | E15: ='P&L'!E23 -> 1210000 | F15: ='P&L'!F23 -> 4620000
A16: Gross Margin % | B16: =IF('P&L'!B7=0,"",'P&L'!B13/'P&L'!B7) | C16: =IF('P&L'!C7=0,"",'P&L'!C13/'P&L'!C7) -> 0.84 | D16: =IF('P&L'!D7=0,"",'P&L'!D13/'P&L'!D7) -> 0.9 | E16: =IF('P&L'!E7=0,"",'P&L'!E13/'P&L'!E7) -> 0.91666667 | F16: =IF('P&L'!F7=0,"",'P&L'!F13/'P&L'!F7) -> 0.92666667
A17: EBITDA Margin % | B17: =IF('P&L'!B7=0,"",'P&L'!B23/'P&L'!B7) | C17: =IF('P&L'!C7=0,"",'P&L'!C23/'P&L'!C7) -> -1.216 | D17: =IF('P&L'!D7=0,"",'P&L'!D23/'P&L'!D7) -> -0.125 | E17: =IF('P&L'!E7=0,"",'P&L'!E23/'P&L'!E7) -> 0.20166667 | F17: =IF('P&L'!F7=0,"",'P&L'!F23/'P&L'!F7) -> 0.308
A19: FUNDING ASK
A20: Amount Sought (₹) | B20: ₹ 30,00,000 (30 Lakhs)
A21: Purpose / Use of Funds | B21: Product Development 50% · Marketing & Pilot Setup 30% · Operations 20%
A22: Current Valuation (₹) | B22: ₹ 3,00,00,000 (3 Crore)
A23: Expected Valuation in 3 Years (₹) | B23: ₹ 15,00,00,000 (15 Crore)
A24: Previous Investors | B24: None (Bootstrapped)
A25: KEY ASSUMPTIONS (briefly describe the logic behind your numbers)
A26: Revenue assumption / pricing logic | B26: Monthly base SaaS fee of ₹15,000 per bank branch + ₹300 per credit appraisal report generated. Highly scalable and affordable for cooperative banks.
A27: Primary cost driver | B27: AI/ML engineering salaries, secure multi-tenant cloud storage (Supabase), and API execution tokens (Groq/Tesseract OCR).
A28: Growth driver (what will scale revenue) | B28: Partnerships with state cooperative bank federations and integration with cloud-based core banking systems.
A29: Key risk and how you will manage it | B29: API latency or server downtime. Managed via a local SQLite fallback database and dual-write replication to prevent any data loss.
A31: Fill YELLOW cells · Blue text = your inputs · Green text = auto-calculated · Black text = formulas (do not edit)

Sheet P&L
A1: VANDE BHARATAM · Profit & Loss Statement (5-Year Projection)
A2: Yellow cells = your inputs · All figures in ₹ · Enter expenses as positive numbers
A3: LINE ITEM | B3: FY 2025-26 | C3: FY 2026-27 | D3: FY 2027-28 | E3: FY 2028-29 | F3: FY 2029-30
A4: REVENUE
A5: Revenue / Sales (Primary) | B5: 0 | C5: 500000 | D5: 2000000 | E5: 6000000 | F5: 15000000
A6: Other Income | B6: 0 | C6: 0 | D6: 0 | E6: 0 | F6: 0
A7: TOTAL REVENUE | B7: =SUM(B5:B6) -> 0 | C7: =SUM(C5:C6) -> 500000 | D7: =SUM(D5:D6) -> 2000000 | E7: =SUM(E5:E6) -> 6000000 | F7: =SUM(F5:F6) -> 15000000
A8: COST OF GOODS SOLD (COGS) — Direct costs to deliver your product/service
A9: Raw Material / Input Cost | B9: 0 | C9: 0 | D9: 0 | E9: 0 | F9: 0
A10: Direct Labour / Outsourcing | B10: 0 | C10: 50000 | D10: 100000 | E10: 250000 | F10: 500000
A11: Other Direct Costs | B11: 10000 | C11: 30000 | D11: 100000 | E11: 250000 | F11: 600000
A12: TOTAL COGS | B12: =SUM(B9:B11) -> 10000 | C12: =SUM(C9:C11) -> 80000 | D12: =SUM(D9:D11) -> 200000 | E12: =SUM(E9:E11) -> 500000 | F12: =SUM(F9:F11) -> 1100000
A13: GROSS PROFIT (Revenue − COGS) | B13: =B7-B12 -> -10000 | C13: =C7-C12 -> 420000 | D13: =D7-D12 -> 1800000 | E13: =E7-E12 -> 5500000 | F13: =F7-F12 -> 13900000
A14: Gross Margin % | B14: =IF(B7=0,"",B13/B7) | C14: =IF(C7=0,"",C13/C7) -> 0.84 | D14: =IF(D7=0,"",D13/D7) -> 0.9 | E14: =IF(E7=0,"",E13/E7) -> 0.91666667 | F14: =IF(F7=0,"",F13/F7) -> 0.92666667
A15: OPERATING EXPENSES
A16: Salaries & Wages | B16: 300000 | C16: 800000 | D16: 1500000 | E16: 3000000 | F16: 6000000
A17: Rent & Utilities | B17: 24000 | C17: 48000 | D17: 120000 | E17: 240000 | F17: 480000
A18: Marketing & Advertising | B18: 30000 | C18: 80000 | D18: 200000 | E18: 500000 | F18: 1500000
A19: Technology / Software | B19: 30000 | C19: 60000 | D19: 150000 | E19: 400000 | F19: 1000000
A20: Depreciation | B20: 0 | C20: 0 | D20: 0 | E20: 0 | F20: 0
A21: Other Expenses | B21: 20000 | C21: 40000 | D21: 80000 | E21: 150000 | F21: 300000
A22: TOTAL OPERATING EXPENSES | B22: =SUM(B16:B21) -> 404000 | C22: =SUM(C16:C21) -> 1028000 | D22: =SUM(D16:D21) -> 2050000 | E22: =SUM(E16:E21) -> 4290000 | F22: =SUM(F16:F21) -> 9280000
A23: EBITDA (Gross Profit − Opex) | B23: =B13-B22 -> -414000 | C23: =C13-C22 -> -608000 | D23: =D13-D22 -> -250000 | E23: =E13-E22 -> 1210000 | F23: =F13-F22 -> 4620000
A24: EBITDA Margin % | B24: =IF(B7=0,"",B23/B7) | C24: =IF(C7=0,"",C23/C7) -> -1.216 | D24: =IF(D7=0,"",D23/D7) -> -0.125 | E24: =IF(E7=0,"",E23/E7) -> 0.20166667 | F24: =IF(F7=0,"",F23/F7) -> 0.308
A26: *fill accurately as many details as you have
